planet_image_acquisition/__init__.py
planet_image_acquisition/date_logic.py
planet_image_acquisition/download.py
planet_image_acquisition/main.py
planet_image_acquisition/raster_analysis.py
planet_image_acquisition/vector_analysis.py
planet_image_acquisition-0.1.dist-info/LICENSE
planet_image_acquisition-0.1.dist-info/METADATA
planet_image_acquisition-0.1.dist-info/WHEEL
planet_image_acquisition-0.1.dist-info/top_level.txt
planet_image_acquisition-0.1.dist-info/RECORD
