Metadata-Version: 2.1
Name: planet_image_acquisition
Version: 0.1
Summary: A package for acquiring and processing Planet images
Home-page: https://github.com/yourusername/planet_image_acquisition
Author: Megharaj Neupane
Author-email: neupanemegh888@gmail.com
Classifier: Programming Language :: Python :: 3
Classifier: License :: OSI Approved :: MIT License
Classifier: Operating System :: OS Independent
Requires-Python: >=3.10
License-File: LICENSE
Requires-Dist: affine==2.4.0
Requires-Dist: attrs==24.2.0
Requires-Dist: certifi==2024.8.30
Requires-Dist: charset-normalizer==3.3.2
Requires-Dist: click==8.1.7
Requires-Dist: click-plugins==1.1.1
Requires-Dist: cligj==0.7.2
Requires-Dist: docutils==0.21.2
Requires-Dist: geopandas==1.0.1
Requires-Dist: glob2==0.7
Requires-Dist: idna==3.8
Requires-Dist: importlib-metadata==8.5.0
Requires-Dist: jaraco.classes==3.4.0
Requires-Dist: jaraco.context==6.0.1
Requires-Dist: jaraco.functools==4.0.2
Requires-Dist: keyring==25.3.0
Requires-Dist: markdown-it-py==3.0.0
Requires-Dist: mdurl==0.1.2
Requires-Dist: more-itertools==10.5.0
Requires-Dist: nh3==0.2.18
Requires-Dist: numpy==2.1.1
Requires-Dist: packaging==24.1
Requires-Dist: pandas==2.2.2
Requires-Dist: pkginfo==1.10.0
Requires-Dist: Pygments==2.18.0
Requires-Dist: pyogrio==0.9.0
Requires-Dist: pyparsing==3.1.4
Requires-Dist: pyproj==3.6.1
Requires-Dist: python-dateutil==2.9.0.post0
Requires-Dist: pytz==2024.2
Requires-Dist: rasterio==1.3.11
Requires-Dist: readme-renderer==44.0
Requires-Dist: requests==2.32.3
Requires-Dist: requests-toolbelt==1.0.0
Requires-Dist: rfc3986==2.0.0
Requires-Dist: rich==13.8.1
Requires-Dist: setuptools==74.1.2
Requires-Dist: shapely==2.0.6
Requires-Dist: six==1.16.0
Requires-Dist: snuggs==1.4.7
Requires-Dist: twine==5.1.1
Requires-Dist: tzdata==2024.1
Requires-Dist: urllib3==2.2.3
Requires-Dist: wheel==0.44.0
Requires-Dist: zipp==3.20.1
